datawhys/__init__.py
datawhys/bot.py
datawhys/conftest.py
datawhys/dd_transformer.py
datawhys/error.py
datawhys/prescriber.py
datawhys/analysis/__init__.py
datawhys/analysis/_what_if.py
datawhys/api/__init__.py
datawhys/api/api.py
datawhys/api/clients.py
datawhys/api/language.py
datawhys/api/meta.py
datawhys/api/requestor.py
datawhys/api/solve.py
datawhys/api/util.py
datawhys/core/__init__.py
datawhys/core/api.py
datawhys/core/frame.py
datawhys/core/meta.py
datawhys/core/series.py
datawhys/datasets/__init__.py
datawhys/datasets/_base.py
datawhys/datasets/data/bank-credit-risk-with-date.csv
datawhys/datasets/data/bronchial-risk.csv
datawhys/datasets/data/iris.csv
datawhys/datasets/data/jets.csv
datawhys/datasets/data/mazda.csv
datawhys/datasets/data/political-behavior.csv
datawhys/datasets/data/shampoo.csv
datawhys/datasets/data/titanic.csv
datawhys/datautils/__init__.py
datawhys/datautils/_apply.py
datawhys/datautils/_decorrelate.py
datawhys/datautils/_sample.py
datawhys/diagnostics/__init__.py
datawhys/diagnostics/_extraction.py
datawhys/diagnostics/_validation.py
datawhys/examples/import.md
datawhys/metrics/__init__.py
datawhys/metrics/_bias.py
datawhys/metrics/_correlation.py
datawhys/metrics/_drift.py
datawhys/metrics/_encoded.py
datawhys/metrics/_score.py
datawhys/metrics/_target.py
datawhys/solver/__init__.py
datawhys/solver/_solver.py
datawhys/solver/meta/__init__.py
datawhys/solver/meta/_solve.py
datawhys/utils/__init__.py
datawhys/utils/constants.py
datawhys/utils/data.py
datawhys/utils/graph.py
datawhys/utils/graphviz.py
datawhys/utils/log.py
datawhys/utils/meta.py
datawhys/utils/utilities.py
datawhys-0.4.1.dist-info/LICENSE
datawhys-0.4.1.dist-info/METADATA
datawhys-0.4.1.dist-info/WHEEL
datawhys-0.4.1.dist-info/top_level.txt
datawhys-0.4.1.dist-info/RECORD
