Metadata-Version: 2.1
Name: datawhys
Version: 0.4.1
Summary: DataWhys API wrapper
Home-page: https://bitbucket.org/mondobrain/datawhys-python
Author: DataWhys
License: MIT License
Project-URL: DataWhys homepage, https://datawhys.ai
Project-URL: DataWhys source, https://bitbucket.org/mondobrain/datawhys-python
Platform: any
Classifier: Development Status :: 3 - Alpha
Classifier: Intended Audience :: Developers
Classifier: Topic :: Software Development
Classifier: Topic :: Scientific/Engineering
Classifier: Natural Language :: English
Classifier: License :: OSI Approved :: MIT License
Classifier: Programming Language :: Python :: 3
Classifier: Programming Language :: Python :: 3.5
Classifier: Programming Language :: Python :: 3.6
Classifier: Programming Language :: Python :: 3.7
Classifier: Programming Language :: Python :: 3.8
Classifier: Operating System :: OS Independent
Classifier: Operating System :: Microsoft :: Windows
Classifier: Operating System :: POSIX
Classifier: Operating System :: Unix
Classifier: Operating System :: MacOS
Requires-Python: >=3.6
License-File: LICENSE
Requires-Dist: networkx (~=2.5)
Requires-Dist: numpy (~=1.18)
Requires-Dist: pandas (~=1.0)
Requires-Dist: pyarrow (~=3.0.0)
Requires-Dist: requests (~=2.7)
Requires-Dist: scikit-learn (~=0.22.1)
Provides-Extra: sci
Requires-Dist: umap-learn (~=0.5.1) ; extra == 'sci'
Provides-Extra: viz
Requires-Dist: graphviz (~=0.14.2) ; extra == 'viz'
Requires-Dist: pygraphviz (~=1.6) ; extra == 'viz'
